suave/__init__.py
suave/_version.py
suave/data.py
suave/defaults.py
suave/evaluate.py
suave/model.py
suave/plots.py
suave/sampling.py
suave/schema_inference.py
suave/types.py
suave/interactive/__init__.py
suave/interactive/schema_builder.py
suave/modules/calibrate.py
suave/modules/decoder.py
suave/modules/distributions.py
suave/modules/encoder.py
suave/modules/heads.py
suave/modules/losses.py
suave/modules/prior.py
suave_ml-0.2.0.dist-info/licenses/LICENSE
suave_ml-0.2.0.dist-info/METADATA
suave_ml-0.2.0.dist-info/WHEEL
suave_ml-0.2.0.dist-info/top_level.txt
suave_ml-0.2.0.dist-info/RECORD
