Metadata-Version: 2.4
Name: suave-ml
Version: 0.2.0
Summary: Hybrid VAE for unified task of prediction, data synthesis, and representation learning
Author: Xuxu Wei
License: Copyright (c) 2025 Xuxu Wei. All rights reserved. 
Project-URL: Homepage, https://github.com/xuxu-wei/SUAVE
Project-URL: Issues, https://github.com/xuxu-wei/SUAVE/issues
Project-URL: Changelog, https://github.com/xuxu-wei/SUAVE/releases
Keywords: VAE,deep learning,data synthesis,pytorch
Classifier: Development Status :: 4 - Beta
Classifier: Intended Audience :: Science/Research
Classifier: Programming Language :: Python :: 3
Classifier: Programming Language :: Python :: 3.9
Classifier: Programming Language :: Python :: 3.10
Classifier: Programming Language :: Python :: 3.11
Classifier: Programming Language :: Python :: 3.12
Classifier: Topic :: Scientific/Engineering :: Artificial Intelligence
Classifier: License :: OSI Approved :: BSD License
Requires-Python: >=3.9
License-File: LICENSE
Requires-Dist: numpy>=1.24
Requires-Dist: pandas>=1.5
Requires-Dist: openpyxl>=3.1
Requires-Dist: matplotlib>=3.7
Requires-Dist: seaborn>=0.12
Requires-Dist: scipy>=1.10
Requires-Dist: statsmodels>=0.14
Requires-Dist: tqdm>=4.65
Requires-Dist: scikit-learn>=1.4
Requires-Dist: optuna>=3.4
Requires-Dist: plotly>=5.18
Requires-Dist: tabulate>=0.9
Requires-Dist: flask<3,>=2.3
Provides-Extra: torch
Requires-Dist: torch>=2.2; extra == "torch"
Dynamic: license-file
